workflow_templater/__init__.py
workflow_templater/common.py
workflow_templater/our_jinja.py
workflow_templater/quote_windows.py
workflow_templater/urlopen_jira.py
workflow_templater-0.2.16.dist-info/LICENSE
workflow_templater-0.2.16.dist-info/METADATA
workflow_templater-0.2.16.dist-info/WHEEL
workflow_templater-0.2.16.dist-info/entry_points.txt
workflow_templater-0.2.16.dist-info/top_level.txt
workflow_templater-0.2.16.dist-info/zip-safe
workflow_templater-0.2.16.dist-info/RECORD
