Metadata-Version: 2.1
Name: workflow-templater
Version: 0.2.16
Summary: Template engine for (currently) Jira and Email. Uses yaml and jinja2. It helps you create multiple (possibly cross-linked) jira issues and emails from a template.
Home-page: https://github.com/m-khvoinitsky/workflow-templater
Author: Mikhail Khvoinitsky
Author-email: me@khvoinitsky.org
Keywords: jira email template workflow release
Classifier: Programming Language :: Python :: 3
Classifier: Programming Language :: Python :: 3 :: Only
Classifier: License :: OSI Approved :: MIT License
Classifier: Operating System :: OS Independent
Classifier: Development Status :: 5 - Production/Stable
Classifier: Environment :: Console
Classifier: Intended Audience :: Information Technology
Classifier: Topic :: Office/Business :: Scheduling
License-File: LICENSE
Requires-Dist: appdirs==1.4.4
Requires-Dist: cffi==1.15.1
Requires-Dist: cryptography==41.0.1
Requires-Dist: importlib-metadata==6.7.0
Requires-Dist: jaraco-classes==3.2.3
Requires-Dist: jeepney==0.8.0
Requires-Dist: jinja2==3.1.2
Requires-Dist: keyring==24.2.0
Requires-Dist: markupsafe==2.1.3
Requires-Dist: more-itertools==9.1.0
Requires-Dist: natsort==8.4.0
Requires-Dist: pycparser==2.21
Requires-Dist: ruamel-yaml==0.17.32
Requires-Dist: ruamel-yaml-clib==0.2.7
Requires-Dist: secretstorage==3.3.3
Requires-Dist: zipp==3.15.0
